PEPit/__init__.py
PEPit/block_partition.py
PEPit/constraint.py
PEPit/expression.py
PEPit/function.py
PEPit/pep.py
PEPit/point.py
PEPit/psd_matrix.py
PEPit/wrapper.py
PEPit/examples/__init__.py
PEPit/examples/example_template.py
PEPit/examples/adaptive_methods/__init__.py
PEPit/examples/adaptive_methods/polyak_steps_in_distance_to_optimum.py
PEPit/examples/adaptive_methods/polyak_steps_in_function_value.py
PEPit/examples/composite_convex_minimization/__init__.py
PEPit/examples/composite_convex_minimization/accelerated_douglas_rachford_splitting.py
PEPit/examples/composite_convex_minimization/accelerated_proximal_gradient.py
PEPit/examples/composite_convex_minimization/accelerated_proximal_gradient_simplified.py
PEPit/examples/composite_convex_minimization/bregman_proximal_point.py
PEPit/examples/composite_convex_minimization/douglas_rachford_splitting.py
PEPit/examples/composite_convex_minimization/douglas_rachford_splitting_contraction.py
PEPit/examples/composite_convex_minimization/frank_wolfe.py
PEPit/examples/composite_convex_minimization/improved_interior_algorithm.py
PEPit/examples/composite_convex_minimization/no_lips_in_bregman_divergence.py
PEPit/examples/composite_convex_minimization/no_lips_in_function_value.py
PEPit/examples/composite_convex_minimization/proximal_gradient.py
PEPit/examples/composite_convex_minimization/proximal_gradient_quadratics.py
PEPit/examples/composite_convex_minimization/three_operator_splitting.py
PEPit/examples/continuous_time_models/__init__.py
PEPit/examples/continuous_time_models/accelerated_gradient_flow_convex.py
PEPit/examples/continuous_time_models/accelerated_gradient_flow_strongly_convex.py
PEPit/examples/continuous_time_models/gradient_flow_convex.py
PEPit/examples/continuous_time_models/gradient_flow_strongly_convex.py
PEPit/examples/fixed_point_problems/__init__.py
PEPit/examples/fixed_point_problems/halpern_iteration.py
PEPit/examples/fixed_point_problems/inconsistent_halpern_iteration.py
PEPit-0.4.0.dist-info/LICENSE
PEPit-0.4.0.dist-info/METADATA
PEPit-0.4.0.dist-info/WHEEL
PEPit-0.4.0.dist-info/top_level.txt
PEPit-0.4.0.dist-info/RECORD
