Metadata-Version: 2.1
Name: PEPit
Version: 0.4.0
Summary: PEPit is a package that allows users to pep their optimization algorithms as easily as they implement them
Home-page: https://github.com/PerformanceEstimation/PEPit
Download-URL: https://github.com/PerformanceEstimation/PEPit/archive/refs/tags/0.4.0.tar.gz
Author: Baptiste Goujaud, Céline Moucer, Julien Hendrickx, Francois Glineur, Adrien Taylor and Aymeric Dieuleveut
Author-email: baptiste.goujaud@gmail.com
Project-URL: Documentation, https://pepit.readthedocs.io/en/0.4.0/
Classifier: Programming Language :: Python :: 3
Classifier: License :: OSI Approved :: MIT License
Classifier: Operating System :: OS Independent
Requires-Python: >=3.9
License-File: LICENSE
Requires-Dist: cvxpy>=1.1.17
Requires-Dist: pandas>=1.0.0
